globalmart_api_ELT/__init__.py
globalmart_api_ELT/api_tasks.py
globalmart_api_datafetch-0.1.dist-info/METADATA
globalmart_api_datafetch-0.1.dist-info/WHEEL
globalmart_api_datafetch-0.1.dist-info/top_level.txt
globalmart_api_datafetch-0.1.dist-info/RECORD
